bda.plone.productshop-1.0b1-py3.9-nspkg.pth
bda/plone/productshop/__init__.py
bda/plone/productshop/behaviors.py
bda/plone/productshop/config.py
bda/plone/productshop/configure.zcml
bda/plone/productshop/content.py
bda/plone/productshop/i18n.sh
bda/plone/productshop/indexer.py
bda/plone/productshop/interfaces.py
bda/plone/productshop/profiles.zcml
bda/plone/productshop/setuphandlers.py
bda/plone/productshop/utils.py
bda/plone/productshop/vocabularies.py
bda/plone/productshop/browser/__init__.py
bda/plone/productshop/browser/actions.py
bda/plone/productshop/browser/actions.zcml
bda/plone/productshop/browser/configure.zcml
bda/plone/productshop/browser/forms.py
bda/plone/productshop/browser/views.py
bda/plone/productshop/browser/resources/dummy_listing_product.jpg
bda/plone/productshop/browser/resources/dummy_product.jpg
bda/plone/productshop/browser/resources/productshop.css
bda/plone/productshop/browser/resources/productshop.css.map
bda/plone/productshop/browser/resources/productshop.js
bda/plone/productshop/browser/resources/productshop.less
bda/plone/productshop/browser/templates/aspects.pt
bda/plone/productshop/browser/templates/listing.pt
bda/plone/productshop/browser/templates/product.pt
bda/plone/productshop/browser/templates/product_listing.pt
bda/plone/productshop/browser/templates/product_tiles.pt
bda/plone/productshop/browser/templates/product_view.pt
bda/plone/productshop/browser/templates/productgroup_listing.pt
bda/plone/productshop/browser/templates/productgroup_view.pt
bda/plone/productshop/browser/templates/tiles.pt
bda/plone/productshop/browser/templates/variant.pt
bda/plone/productshop/browser/templates/variant_view.pt
bda/plone/productshop/locales/bda.plone.productshop.pot
bda/plone/productshop/locales/de/LC_MESSAGES/bda.plone.productshop.po
bda/plone/productshop/locales/en/LC_MESSAGES/bda.plone.productshop.po
bda/plone/productshop/locales/it/LC_MESSAGES/bda.plone.productshop.po
bda/plone/productshop/profiles/default/actions.xml
bda.plone.productshop-1.0b1.dist-info/LICENSE.rst
bda.plone.productshop-1.0b1.dist-info/LICENSE_GPL.rst
bda.plone.productshop-1.0b1.dist-info/METADATA
bda.plone.productshop-1.0b1.dist-info/WHEEL
bda.plone.productshop-1.0b1.dist-info/entry_points.txt
bda.plone.productshop-1.0b1.dist-info/namespace_packages.txt
bda.plone.productshop-1.0b1.dist-info/top_level.txt
bda.plone.productshop-1.0b1.dist-info/RECORD
