Metadata-Version: 2.1
Name: bda.plone.productshop
Version: 1.0b1
Summary: Product shop extension based on bda.plone.shop
Home-page: https://github.com/bluedynamics/bda.plone.productshop
Author: Bluedynamics Alliance
Author-email: dev@bluedynamics.com
License: GPL version 2
Project-URL: PyPI, https://pypi.python.org/pypi/bda.plone.productshop
Project-URL: Source, https://github.com/bluedynamics/bda.plone.productshop
Project-URL: Tracker, https://github.com/bluedynamics/bda.plone.productshop/issues
Keywords: Python Plone e-commerce
Classifier: Framework :: Plone
Classifier: Framework :: Plone :: 6.0
Classifier: Framework :: Plone :: Addon
Classifier: Framework :: Zope
Classifier: Framework :: Zope :: 5
Classifier: License :: OSI Approved :: GNU General Public License (GPL)
Classifier: Programming Language :: Python
Classifier: Programming Language :: Python :: 3.8
Classifier: Programming Language :: Python :: 3.9
Classifier: Programming Language :: Python :: 3.10
Classifier: Programming Language :: Python :: 3.11
Classifier: Programming Language :: Python :: 3.12
Classifier: Topic :: Software Development :: Libraries :: Python Modules
License-File: LICENSE.rst
License-File: LICENSE_GPL.rst
Requires-Dist: setuptools
Requires-Dist: Products.CMFPlone >=6.0.0
Requires-Dist: bda.plone.shop
Requires-Dist: collective.instancebehavior
Provides-Extra: test
Requires-Dist: plone.app.testing ; extra == 'test'
Requires-Dist: plone.app.robotframework[debug] ; extra == 'test'
